xmlgenerator/__init__.py
xmlgenerator/arguments.py
xmlgenerator/bootstrap.py
xmlgenerator/configuration.py
xmlgenerator/generator.py
xmlgenerator/randomization.py
xmlgenerator/substitution.py
xmlgenerator/validation.py
xmlgenerator-0.9.0.dist-info/licenses/LICENSE
xmlgenerator-0.9.0.dist-info/METADATA
xmlgenerator-0.9.0.dist-info/WHEEL
xmlgenerator-0.9.0.dist-info/entry_points.txt
xmlgenerator-0.9.0.dist-info/top_level.txt
xmlgenerator-0.9.0.dist-info/RECORD
