Metadata-Version: 2.4
Name: xmlgenerator
Version: 0.9.0
Summary: Generates XML documents from XSD schemas
Home-page: https://github.com/lexakimov/xmlgenerator
Author: Alexey Akimov
Author-email: lex.akimov23@gmail.com
License: MIT
Classifier: Programming Language :: Python :: 3
Classifier: Operating System :: OS Independent
Requires-Python: >=3.10
License-File: LICENSE
Requires-Dist: lxml
Requires-Dist: xmlschema
Requires-Dist: Faker
Requires-Dist: rstr
Requires-Dist: PyYAML
Requires-Dist: shtab
Dynamic: author
Dynamic: author-email
Dynamic: classifier
Dynamic: description
Dynamic: description-content-type
Dynamic: home-page
Dynamic: license
Dynamic: license-file
Dynamic: requires-dist
Dynamic: requires-python
Dynamic: summary
